Metadata-Version: 2.1
Name: FileAnalysis
Version: 0.0.2
Summary: This package analyze emergence of characters in file (for statistics decryption).
Home-page: https://github.com/mauricelambert/FileAnalysis/
Author: Maurice Lambert
Author-email: mauricelambert434@gmail.com
Maintainer: Maurice Lambert
Maintainer-email: mauricelambert434@gmail.com
License: GPL-3.0 License
Download-URL: https://mauricelambert.github.io/info/python/security/FileAnalysis.pyz
Project-URL: Executable, https://mauricelambert.github.io/info/python/security/FileAnalysis.pyz
Project-URL: Documentation, https://mauricelambert.github.io/info/python/security/FileAnalysis.html
Keywords: Decryption
Platform: Windows
Platform: Linux
Platform: MacOS
Classifier: Programming Language :: Python
Classifier: Development Status :: 5 - Production/Stable
Classifier: Environment :: Console
Classifier: Natural Language :: English
Classifier: Programming Language :: Python :: 3.9
Classifier: Operating System :: POSIX :: Linux
Classifier: Operating System :: Microsoft :: Windows
Classifier: Operating System :: MacOS
Classifier: Topic :: Security
Classifier: Topic :: Security :: Cryptography
Requires-Python: >=3.6
